<?xml version="1.0" encoding="UTF-8" standalone="yes"?>
<items>

<item>
<title>[COLOR silver][B]Federer: Doze Últimos Dias Legendado 2024[/B][/COLOR][COLOR yellow] FULL HD 4K[/COLOR]</title>
<link>plugin://plugin.video.elementum/play?uri=magnet:?xt=urn:btih:G5Z3W2JSUKFP45RHQL4AP2XRWDB46ZDH$$lsname=[COLOR white]TORRENT 4K[/COLOR]</link>
<link>plugin://plugin.video.youtube/play/?video_id=ctbUL__L60o$$lsname=[COLOR aquamarine]TRAILER[/COLOR]</link>
<thumbnail>https://image.tmdb.org/t/p/w500/wsQZfYVCbjNco4zm5AxI7yXuS2B.jpg</thumbnail>
<fanart>https://image.tmdb.org/t/p/w1280/sIwhdAN3sqk3oK1fUORqbrG4aEn.jpg</fanart>
<info>
[COLOR yellow]Título Original:[/COLOR] Federer: Twelve Final Days
[COLOR yellow]Elenco Principal:[/COLOR] Roger Federer, Rafael Nadal, Novak Djokovic, Andy Murray, Mirka Federer
[COLOR yellow]Duração:[/COLOR] 1h 28min
[COLOR yellow]Diretor:[/COLOR] Asif Kapadia
[COLOR yellow]Ano:[/COLOR] 2024
[COLOR yellow]Nota:[/COLOR] 7.6
[COLOR yellow]Gênero:[/COLOR] Documentário
[COLOR yellow]Sinopse:[/COLOR] Originalmente um vídeo caseiro nunca destinado ao público, este filme captura o capítulo final da lendária carreira de Roger Federer no tênis, apresentando Roger, sua família e seus três principais rivais: Rafael Nadal, Novak Djokovic e Andy Murray.

</info>
</item>

<item>
<title>[COLOR silver][B]Ferrari Legendado (2019)[/B][/COLOR][COLOR yellow] FULL HD[/COLOR]</title>
<link>plugin://plugin.video.elementum/play?uri=magnet:?xt=urn:btih:NZRAJ4Y7RSXUPKQS25U55O5ZN6A3EONW&dn=Ferrari.2023.2160p.WEB.h265-ETHEL%5BTGx%5D&tr=udp%3A%2F%2Fopen.stealth.si%3A80%2Fannounce$$lsname=[COLOR white]TORRENT[/COLOR]</link>
<link>plugin://plugin.video.youtube/play/?video_id=ERAhei9_Ekc$$lsname=[COLOR aquamarine]TRAILER[/COLOR]</link>
<thumbnail>https://image.tmdb.org/t/p/w500/gwvIirDw4fKy491PpjSMda28SoN.jpg</thumbnail>
<fanart>https://image.tmdb.org/t/p/w1280/Ac3rRrduoKoXwQ6ZDgWh8euKhN5.jpg</fanart>
<info>
[COLOR yellow]Título Original:[/COLOR] Ferrari
[COLOR yellow]Elenco Principal:[/COLOR] Adam Driver, Penélope Cruz, Shailene Woodley, Gabriel Leone, Sarah Gadon
[COLOR yellow]Duração:[/COLOR] 2h 11min
[COLOR yellow]Diretor:[/COLOR] Michael Mann
[COLOR yellow]Ano:[/COLOR] 2023
[COLOR yellow]Nota:[/COLOR] 6.4
[COLOR yellow]Gênero:[/COLOR] História, Drama
[COLOR yellow]Sinopse:[/COLOR] O ex-piloto de corrida, Enzo Ferrari está em crise. A falência assombra a empresa que ele e sua mulher, Laura, construíram do nada 10 anos atrás. O casamento tempestuoso dos dois sofre com o luto pela morte de um filho e a dificuldade de reconhecer outro. Ele decide contrapor essas perdas apostando tudo em uma corrida - a icônica Mille Miglia, na Itália.

</info>
</item>




  
</items>
